[
  {
    "id": 1,
    "image": "https://coins.game/const/jetgames/jpeg/1x/crash-v.jpeg",
    "gameName" : "crash",
    "gameReferUrl" : "#"
  },
  {
    "id": 2,
    "image": "https://coins.game/const/jetgames/jpeg/1x/crash-v.jpeg",
    "gameName" : "crash",
    "gameReferUrl" : "#"
  },
  {
    "id": 3,
    "image": "https://coins.game/const/jetgames/jpeg/1x/crash-v.jpeg",
    "gameName" : "crash",
    "gameReferUrl" : "#"
  },
  {
    "id": 4,
    "image": "https://coins.game/const/jetgames/jpeg/1x/crash-v.jpeg",
    "gameName" : "crash",
    "gameReferUrl" : "#"
  },
  {
    "id": 5,
    "image": "https://coins.game/const/jetgames/jpeg/1x/crash-v.jpeg",
    "gameName" : "crash",
    "gameReferUrl" : "#"
  },
  {
    "id": 6,
    "image": "https://coins.game/const/jetgames/jpeg/1x/crash-v.jpeg",
    "gameName" : "crash",
    "gameReferUrl" : "#"
  },
  {
    "id": 7,
    "image": "https://coins.game/const/jetgames/jpeg/1x/crash-v.jpeg",
    "gameName" : "crash",
    "gameReferUrl" : "#"
  },
  {
    "id": 8,
    "image": "https://coins.game/const/jetgames/jpeg/1x/crash-v.jpeg",
    "gameName" : "crash",
    "gameReferUrl" : "#"
  },
  {
    "id": 9,
    "image": "https://coins.game/const/jetgames/jpeg/1x/crash-v.jpeg",
    "gameName" : "crash",
    "gameReferUrl" : "#"
  },
  {
    "id": 10,
    "image": "https://coins.game/const/jetgames/jpeg/1x/crash-v.jpeg",
    "gameName" : "crash",
    "gameReferUrl" : "#"
  }
]
